astm/__init__.py
astm/client.py
astm/codec.py
astm/compat.py
astm/constants.py
astm/exceptions.py
astm/mapping.py
astm/records.py
astm/server.py
astm/version.py
astm/omnilab/__init__.py
astm/omnilab/client.py
astm/omnilab/common.py
astm/omnilab/server.py
astm/tests/__init__.py
astm/tests/test_asynclib.py
astm/tests/test_client.py
astm/tests/test_codecs.py
astm/tests/test_mapping.py
astm/tests/test_omnilab.py
astm/tests/test_protocol.py
astm/tests/test_server.py
astm/tests/utils.py
astmio-1.0.0a3.dist-info/licenses/LICENSE
astmio-1.0.0a3.dist-info/licenses/LICENSE.original
astmio-1.0.0a3.dist-info/METADATA
astmio-1.0.0a3.dist-info/WHEEL
astmio-1.0.0a3.dist-info/top_level.txt
astmio-1.0.0a3.dist-info/RECORD
