Metadata-Version: 2.4
Name: astmio
Version: 1.0.0a3
Summary: Python implementation of ASTM E1381/1394 protocol.
Author-email: Prasoon Pratham <prathamprasoonyt@gmail.com>
Project-URL: Homepage, https://github.com/PrasoonPratham/astmio
Project-URL: Bug Tracker, https://github.com/PrasoonPratham/astmio/issues
Classifier: Development Status :: 4 - Beta
Classifier: Intended Audience :: Developers
Classifier: License :: OSI Approved :: MIT License
Classifier: Operating System :: OS Independent
Classifier: Programming Language :: Python :: 3
Classifier: Programming Language :: Python :: 3.8
Classifier: Programming Language :: Python :: 3.9
Classifier: Programming Language :: Python :: 3.10
Classifier: Programming Language :: Python :: 3.11
Classifier: Programming Language :: Python :: 3.12
Classifier: Programming Language :: Python :: 3.13
Classifier: Topic :: Software Development :: Libraries :: Python Modules
Requires-Python: >=3.8
License-File: LICENSE
License-File: LICENSE.original
Dynamic: license-file
